dartcms/__init__.py
dartcms/context_processors.py
dartcms/urls.py
dartcms/apps/__init__.py
dartcms/apps/ads/__init__.py
dartcms/apps/ads/abstract_models.py
dartcms/apps/ads/admin.py
dartcms/apps/ads/apps.py
dartcms/apps/ads/models.py
dartcms/apps/ads/ad/__init__.py
dartcms/apps/ads/ad/urls.py
dartcms/apps/ads/adplace/__init__.py
dartcms/apps/ads/adplace/urls.py
dartcms/apps/ads/adsection/__init__.py
dartcms/apps/ads/adsection/urls.py
dartcms/apps/ads/migrations/0001_initial.py
dartcms/apps/ads/migrations/0002_auto_20170829_0515.py
dartcms/apps/ads/migrations/__init__.py
dartcms/apps/ads/templatetags/__init__.py
dartcms/apps/ads/templatetags/ads.py
dartcms/apps/auth/__init__.py
dartcms/apps/auth/backends.py
dartcms/apps/auth/forms.py
dartcms/apps/auth/mixins.py
dartcms/apps/auth/urls.py
dartcms/apps/auth/utils.py
dartcms/apps/auth/views.py
dartcms/apps/dashboard/__init__.py
dartcms/apps/dashboard/urls.py
dartcms/apps/dashboard/views.py
dartcms/apps/dicts/__init__.py
dartcms/apps/dicts/urls.py
dartcms/apps/feedback/__init__.py
dartcms/apps/feedback/abstract_models.py
dartcms/apps/feedback/admin.py
dartcms/apps/feedback/apps.py
dartcms/apps/feedback/config.py
dartcms/apps/feedback/models.py
dartcms/apps/feedback/urls.py
dartcms/apps/feedback/messages/__init__.py
dartcms/apps/feedback/messages/urls.py
dartcms/apps/feedback/messages/views.py
dartcms/apps/feedback/migrations/0001_initial.py
dartcms/apps/feedback/migrations/0002_auto_20160713_0349.py
dartcms/apps/feedback/migrations/0003_auto_20160801_1607.py
dartcms/apps/feedback/migrations/0004_auto_20170829_0515.py
dartcms/apps/feedback/migrations/__init__.py
dartcms/apps/feeds/__init__.py
dartcms/apps/feeds/abstract_models.py
dartcms/apps/feeds/admin.py
dartcms/apps/feeds/apps.py
dartcms/apps/feeds/models.py
dartcms/apps/feeds/urls.py
dartcms/apps/feeds/items/__init__.py
dartcms/apps/feeds/items/forms.py
dartcms/apps/feeds/items/urls.py
dartcms-0.1.9.dist-info/DESCRIPTION.rst
dartcms-0.1.9.dist-info/METADATA
dartcms-0.1.9.dist-info/RECORD
dartcms-0.1.9.dist-info/WHEEL
dartcms-0.1.9.dist-info/metadata.json
dartcms-0.1.9.dist-info/top_level.txt
