Metadata-Version: 2.0
Name: dartcms
Version: 0.1.9
Summary: DartCMS - open-source content management system for Django
Home-page: https://github.com/astrikov-d/dartcms
Author: Dmitry Astrikov
Author-email: astrikov.d@gmail.com
License: MIT License
Keywords: django cms dartcms
Platform: UNKNOWN
Classifier: Development Status :: 3 - Alpha
Classifier: Intended Audience :: Developers
Classifier: Natural Language :: English
Classifier: Programming Language :: Python
Classifier: Programming Language :: Python :: 3.6
Requires-Dist: Django (>=2.0.0)
Requires-Dist: Pillow (>=3.2.0)
Requires-Dist: django-autoslug-iplweb (>=1.9.4.dev0)
Requires-Dist: django-extra-views (>=0.7.1)
Requires-Dist: django-form-utils (>=1.0.3)
Requires-Dist: django-gravatar2 (>=1.4.0)
Requires-Dist: django-mptt (>=0.8.4)
Requires-Dist: django-versatileimagefield (>=1.9)
Requires-Dist: django-widget-tweaks (>=1.4.1)
Requires-Dist: jsonfield (>=1.0.3)
Requires-Dist: pytils (>=0.3)
